vizlab_data_transfer/__init__.py
vizlab_data_transfer/vizlab.py
vizlab_data_transfer-0.2.2.dist-info/METADATA
vizlab_data_transfer-0.2.2.dist-info/WHEEL
vizlab_data_transfer-0.2.2.dist-info/top_level.txt
vizlab_data_transfer-0.2.2.dist-info/RECORD
