Metadata-Version: 2.4
Name: vizlab_data_transfer
Version: 0.2.2
Summary: A small package for sending and receiving data to and from the CTAC VizLab.
Author-email: Chris Couto <ccouto@carnegiescience.edu>
License-Expression: MIT
Project-URL: Repository, https://github.com/carnegie/vizlab-data-transfer
Requires-Python: >=3.7
Requires-Dist: matplotlib
Requires-Dist: Pillow
Requires-Dist: numpy
Requires-Dist: pandas
Requires-Dist: astropy
